Metadata-Version: 2.1
Name: appthreat-depscan
Version: 4.2.3
Summary: Fully open-source security audit for project dependencies based on known vulnerabilities and advisories.
Author-email: Team AppThreat <cloud@appthreat.com>
License: MIT
Project-URL: Homepage, https://github.com/appthreat/dep-scan
Classifier: Development Status :: 5 - Production/Stable
Classifier: Intended Audience :: Developers
Classifier: Intended Audience :: System Administrators
Classifier: License :: OSI Approved :: MIT License
Classifier: Operating System :: OS Independent
Classifier: Programming Language :: Python :: 3.8
Classifier: Programming Language :: Python :: 3.9
Classifier: Programming Language :: Python :: 3.10
Classifier: Programming Language :: Python :: 3.11
Classifier: Topic :: Security
Classifier: Topic :: Utilities
Requires-Python: >=3.8
License-File: LICENSE
Requires-Dist: appthreat-vulnerability-db >=5.2.5
Requires-Dist: defusedxml
Requires-Dist: PyYAML
Requires-Dist: rich
Requires-Dist: quart
Provides-Extra: dev
Requires-Dist: black ; extra == 'dev'
Requires-Dist: flake8 ; extra == 'dev'
Requires-Dist: pytest ; extra == 'dev'
Requires-Dist: pytest-cov ; extra == 'dev'
